BeihangChengxushejiYuyanYuanliJiaocaiGong18Zhang/README.md
BeihangChengxushejiYuyanYuanliJiaocaiGong18Zhang/__init__.py
BeihangChengxushejiYuyanYuanliJiaocaiGong18Zhang/__main__.py
BeihangChengxushejiYuyanYuanliJiaocaiGong18Zhang/file.pdf
BeihangChengxushejiYuyanYuanliJiaocaiGong18Zhang/index.html
beihang_chengxusheji_yuyan_yuanli_jiaocai_gong_18_zhang-2024.3.2.0.dist-info/METADATA
beihang_chengxusheji_yuyan_yuanli_jiaocai_gong_18_zhang-2024.3.2.0.dist-info/WHEEL
beihang_chengxusheji_yuyan_yuanli_jiaocai_gong_18_zhang-2024.3.2.0.dist-info/entry_points.txt
beihang_chengxusheji_yuyan_yuanli_jiaocai_gong_18_zhang-2024.3.2.0.dist-info/top_level.txt
beihang_chengxusheji_yuyan_yuanli_jiaocai_gong_18_zhang-2024.3.2.0.dist-info/RECORD
